{
  "timestamp": "2026-03-18T22:50:03.101911",
  "cognitive_score": 32,
  "status_code": "medium",
  "status_text": "\ud83d\udfe1 \u8f7b\u8d1f\u8f7d",
  "suggestion": "30\u79d2\u5185\u54cd\u5e94",
  "active_sessions": 2,
  "pending_count": 1,
  "processing_count": 1,
  "github_workflows": 0,
  "local_builds": 0,
  "max_wait_sec": 3002,
  "total_tokens": 173754,
  "total_tokens_formatted": "173k",
  "estimated_response": 3002,
  "estimated_response_formatted": "3002s",
  "last_active_sec": 1,
  "task_queue": [
    {
      "label": "\ud83d\udcac \u6218\u68cb\u7814\u7a76",
      "status": "\ud83d\udca4 50\u5206\u949f\u524d\u6d3b\u8dc3",
      "tokens": 2842
    },
    {
      "label": "\ud83d\udc65 GitHub\u64cd\u4f5c",
      "status": "\ud83d\udd04 \u5904\u7406\u4e2d",
      "tokens": 170912
    }
  ],
  "cpu_percent": 1.5,
  "memory_percent": 42.6,
  "workflow_details": [],
  "build_details": []
}