{
  "timestamp": "2026-03-18T09:34:02.163583",
  "cognitive_score": 25,
  "status_code": "low",
  "status_text": "\ud83d\udfe2 \u7a7a\u95f2",
  "suggestion": "\u53ef\u7acb\u5373\u54cd\u5e94",
  "active_sessions": 2,
  "pending_count": 1,
  "processing_count": 0,
  "github_workflows": 0,
  "local_builds": 0,
  "max_wait_sec": 2041,
  "total_tokens": 3583,
  "total_tokens_formatted": "3k",
  "estimated_response": 2041,
  "estimated_response_formatted": "2041s",
  "last_active_sec": 1805,
  "task_queue": [
    {
      "label": "\ud83d\udcac \u4efb\u52a1\u8c03\u5ea6",
      "status": "\ud83d\udd34 \u7b49\u5f8534\u5206\u949f",
      "tokens": 165
    },
    {
      "label": "\ud83d\udc65 \u98de\u4e66\u96c6\u6210",
      "status": "\u2705 \u5df2\u56de\u590d",
      "tokens": 3418
    }
  ],
  "cpu_percent": 0.0,
  "memory_percent": 40.6,
  "workflow_details": [],
  "build_details": []
}